{
	"animations": [
		{
			"offsets": [
				0,
				-9
			],
			"loop": false,
			"fps": 13,
			"anim": "danceLeft",
			"indices": [],
			"image": "",
			"name": "dance left"
		},
		{
			"offsets": [
				0,
				-9
			],
			"loop": false,
			"fps": 13,
			"anim": "danceRight",
			"indices": [],
			"image": "",
			"name": "dance right"
		}
	],
	"sing_anims_prefix": "sing",
	"no_antialiasing": true,
	"healthicon_scale": 1,
	"gameover_properties": [
		"bf-dead",
		"fnf_loss_sfx",
		"gameOver",
		"gameOverEnd"
	],
	"image": "characters/BeatdropGF",
	"position": [
		0,
		-100
	],
	"healthicon_offsets": [
		0,
		0
	],
	"healthbar_colors2": [
		165,
		0,
		77
	],
	"healthicon": "gf",
	"flip_x": false,
	"healthbar_colors": [
		165,
		0,
		77
	],
	"camera_position": [
		0,
		0
	],
	"sing_duration": 4,
	"scale": 1
}